pattern/PATTERN_Iota.v
//############################################################################
//
//   Author      : Po-Wei Huang
//
//++++++++++++++++++++++++++++++++++++++++++++++++++++++++++++++++++++++++++++
//
//   File Name   : PATTERN_Iota.v
//   Module Name : PATTERN_Iota
//   Release version : v1.0
//
//++++++++++++++++++++++++++++++++++++++++++++++++++++++++++++++++++++++++++++
//############################################################################

`timescale 1ns/10ps
`define CYCLE_TIME 10
`define End_CYCLE  100000000

module PATTERN_Iota(
	clk,
	in_data,
	in_round,
	out_data
);

// ===============================================================
// Input & Output Declaration
// ===============================================================
output reg clk;
output reg [63:0] in_data;
output reg [4:0] in_round;
input out_valid;
input [63:0] out_data;

// ===============================================================
// Parameters & Integer Declaration
// ===============================================================
integer golden_read;
integer patcount,output_count;
integer gap;
integer a;
integer i, j;
parameter PATNUM = 70; // change after
// ===============================================================
// Wire & Reg Declaration
// ===============================================================
reg [1599:0] in_data_all_reg;
reg [63:0] in_data_reg[0:24];
reg [4:0] in_round_reg;
reg [1599:0] out_data_all_reg;
reg [63:0] out_data_reg[0:24];
wire [63:0] test;
assign test = out_data_all_reg[63:0];



// ===============================================================
// Clock
// ===============================================================
always	#(`CYCLE_TIME/2.0) clk = ~clk;
initial	clk = 0;

// ===============================================================
// Initial
// ===============================================================
initial begin
	
	golden_read  = $fopen("./testcase/iota_tb.txt","r");
	@(negedge clk);

	//a = $fscanf(golden_read, "%d", PATNUM);
	for (patcount=0;patcount<PATNUM;patcount=patcount+1) begin		
		load_golden;
		input_task;
		check_answer;
		@(negedge clk);
	end
	#(1000);
	$display("Pass");
	$finish;
end 

// ===============================================================
// TASK
// ===============================================================


task load_golden; begin
	a = $fscanf(golden_read, "%d\n", in_round_reg );
	a = $fscanf(golden_read, "%h\n", in_data_all_reg );
	a = $fscanf(golden_read, "%h\n", out_data_all_reg);

	
end endtask
 
task input_task;begin
	@(negedge clk);
	in_data = in_data_reg[0];
	in_round = in_round_reg;
end endtask

task check_answer;begin
	#(10);
	if(out_data!==out_data_reg[0])begin
		$display ("----------------------------------------------------------------------");
		$display ("  FAIL %2d\n                						                     ",patcount);
		$display ("  Oops! Your Answer is Wrong                						     ");
 		$display ("  [Correct Answer] %h\n                 					             ",out_data_reg[0]);
 		$display ("  [Your Answer] %h\n                 						         ",out_data);
 		$display ("--------------------------------------------------------------------- ");
 		$finish;
 	end
 	else begin
 		$display("\033[1;32mPass \033[1;0mNo. %2d\n",patcount);
 		$display ("  [Your Answer] %h\n                 						         ",out_data);
 		$display ("----------------------------------------------------------------------");
 	end
end endtask




always@(*)begin
	in_data_reg[24] =  in_data_all_reg[64*0 +63:64*0 +0];
	in_data_reg[23] =  in_data_all_reg[64*1 +63:64*1 +0];
	in_data_reg[22] =  in_data_all_reg[64*2 +63:64*2 +0];
	in_data_reg[21] =  in_data_all_reg[64*3 +63:64*3 +0];
	in_data_reg[20] =  in_data_all_reg[64*4 +63:64*4 +0];
	in_data_reg[19] =  in_data_all_reg[64*5 +63:64*5 +0];
	in_data_reg[18] =  in_data_all_reg[64*6 +63:64*6 +0];
	in_data_reg[17] =  in_data_all_reg[64*7 +63:64*7 +0];
	in_data_reg[16] =  in_data_all_reg[64*8 +63:64*8 +0];
	in_data_reg[15] =  in_data_all_reg[64*9 +63:64*9 +0];
	in_data_reg[14] = in_data_all_reg[64*10+63:64*10+0];
	in_data_reg[13] = in_data_all_reg[64*11+63:64*11+0];
	in_data_reg[12] = in_data_all_reg[64*12+63:64*12+0];
	in_data_reg[11] = in_data_all_reg[64*13+63:64*13+0];
	in_data_reg[10] = in_data_all_reg[64*14+63:64*14+0];
	in_data_reg[9 ] = in_data_all_reg[64*15+63:64*15+0];
	in_data_reg[8 ] = in_data_all_reg[64*16+63:64*16+0];
	in_data_reg[7 ] = in_data_all_reg[64*17+63:64*17+0];
	in_data_reg[6 ] = in_data_all_reg[64*18+63:64*18+0];
	in_data_reg[5 ] = in_data_all_reg[64*19+63:64*19+0];
	in_data_reg[4 ] = in_data_all_reg[64*20+63:64*20+0];
	in_data_reg[3 ] = in_data_all_reg[64*21+63:64*21+0];
	in_data_reg[2 ] = in_data_all_reg[64*22+63:64*22+0];
	in_data_reg[1 ] = in_data_all_reg[64*23+63:64*23+0];
	in_data_reg[0 ] = in_data_all_reg[64*24+63:64*24+0];

	out_data_reg[24] =  out_data_all_reg[64*0 +63:64*0 +0];
	out_data_reg[23] =  out_data_all_reg[64*1 +63:64*1 +0];
	out_data_reg[22] =  out_data_all_reg[64*2 +63:64*2 +0];
	out_data_reg[21] =  out_data_all_reg[64*3 +63:64*3 +0];
	out_data_reg[20] =  out_data_all_reg[64*4 +63:64*4 +0];
	out_data_reg[19] =  out_data_all_reg[64*5 +63:64*5 +0];
	out_data_reg[18] =  out_data_all_reg[64*6 +63:64*6 +0];
	out_data_reg[17] =  out_data_all_reg[64*7 +63:64*7 +0];
	out_data_reg[16] =  out_data_all_reg[64*8 +63:64*8 +0];
	out_data_reg[15] =  out_data_all_reg[64*9 +63:64*9 +0];
	out_data_reg[14] = out_data_all_reg[64*10+63:64*10+0];
	out_data_reg[13] = out_data_all_reg[64*11+63:64*11+0];
	out_data_reg[12] = out_data_all_reg[64*12+63:64*12+0];
	out_data_reg[11] = out_data_all_reg[64*13+63:64*13+0];
	out_data_reg[10] = out_data_all_reg[64*14+63:64*14+0];
	out_data_reg[9 ] = out_data_all_reg[64*15+63:64*15+0];
	out_data_reg[8 ] = out_data_all_reg[64*16+63:64*16+0];
	out_data_reg[7 ] = out_data_all_reg[64*17+63:64*17+0];
	out_data_reg[6 ] = out_data_all_reg[64*18+63:64*18+0];
	out_data_reg[5 ] = out_data_all_reg[64*19+63:64*19+0];
	out_data_reg[4 ] = out_data_all_reg[64*20+63:64*20+0];
	out_data_reg[3 ] = out_data_all_reg[64*21+63:64*21+0];
	out_data_reg[2 ] = out_data_all_reg[64*22+63:64*22+0];
	out_data_reg[1 ] = out_data_all_reg[64*23+63:64*23+0];
	out_data_reg[0 ] = out_data_all_reg[64*24+63:64*24+0];
end
endmodule

src/Iota.v
module Iota
(
 clk,
 in_data,
 in_round,
 out_data
);
// ===============================================================
// Input & Output Declaration
// ===============================================================
input clk;
input [63:0]in_data;
input [4:0]in_round;
output [63:0]out_data;
// ===============================================================
// Parameter & Integer Declaration
// ===============================================================

integer i;

parameter KC_0  = 64'h0000000000000001;
parameter KC_1  = 64'h0000000000008082;
parameter KC_2  = 64'h800000000000808a;
parameter KC_3  = 64'h8000000080008000;
parameter KC_4  = 64'h000000000000808b;
parameter KC_5  = 64'h0000000080000001;
parameter KC_6  = 64'h8000000080008081;
parameter KC_7  = 64'h8000000000008009;
parameter KC_8  = 64'h000000000000008a;
parameter KC_9  = 64'h0000000000000088;
parameter KC_10 = 64'h0000000080008009;
parameter KC_11 = 64'h000000008000000a;
parameter KC_12 = 64'h000000008000808b;
parameter KC_13 = 64'h800000000000008b;
parameter KC_14 = 64'h8000000000008089;
parameter KC_15 = 64'h8000000000008003;
parameter KC_16 = 64'h8000000000008002;
parameter KC_17 = 64'h8000000000000080;
parameter KC_18 = 64'h000000000000800a;
parameter KC_19 = 64'h800000008000000a;
parameter KC_20 = 64'h8000000080008081;
parameter KC_21 = 64'h8000000000008080;
parameter KC_22 = 64'h0000000080000001;
parameter KC_23 = 64'h8000000080008008;


//================================================================
// Wire & Reg Declaration
//================================================================
reg [63:0]sel_kc;
//================================================================
// DESIGN
//================================================================

always@(*)begin
	case(in_round)
		0: sel_kc = KC_0;
		1: sel_kc = KC_1;
		2: sel_kc = KC_2;
		3: sel_kc = KC_3;
		4: sel_kc = KC_4;
		5: sel_kc = KC_5;
		6: sel_kc = KC_6;
		7: sel_kc = KC_7;
		8: sel_kc = KC_8;
		9: sel_kc = KC_9;
		10: sel_kc = KC_10;
		11: sel_kc = KC_11;
		12: sel_kc = KC_12;
		13: sel_kc = KC_13;
		14: sel_kc = KC_14;
		15: sel_kc = KC_15;
		16: sel_kc = KC_16;
		17: sel_kc = KC_17;
		18: sel_kc = KC_18;
		19: sel_kc = KC_19;
		20: sel_kc = KC_20;
		21: sel_kc = KC_21;
		22: sel_kc = KC_22;
		23: sel_kc = KC_23;
		default sel_kc = 64'h1;
	endcase
end

assign out_data = in_data ^ sel_kc;

endmodule

testbed/TESTBED_Iota.v
`include "./pattern/PATTERN_Iota.v"
`include "./src/Iota.v"
module TESTBED_Iota();




wire clk;
wire [63:0]in_data;
wire [4:0]in_round;
wire [63:0]out_data;

Iota U_Iota
(
	.clk(clk),
	.in_data(in_data),
	.in_round(in_round),
	.out_data(out_data)
);


PATTERN_Iota U_PATTERN_Iota
(
	.clk(clk),
	.in_data(in_data),
	.in_round(in_round),
	.out_data(out_data)
);

integer i;
initial begin
	$dumpfile("./vcd/Iota.vcd"); // Name your VCD file
    	$dumpvars(0, TESTBED_Iota); // Dump signals starting at time 0
end

endmodule

vcd/Iota.vcd
$date
	Fri Apr 26 19:40:32 2024
$end
$version
	Icarus Verilog
$end
$timescale
	10ps
$end
$scope module TESTBED_Iota $end
$var wire 64 ! out_data [63:0] $end
$var wire 5 " in_round [4:0] $end
$var wire 64 # in_data [63:0] $end
$var wire 1 $ clk $end
$scope module U_Iota $end
$var wire 64 % out_data [63:0] $end
$var wire 5 & in_round [4:0] $end
$var wire 64 ' in_data [63:0] $end
$var wire 1 $ clk $end
$var reg 64 ( sel_kc [63:0] $end
$upscope $end
$scope module U_PATTERN_Iota $end
$var wire 64 ) out_data [63:0] $end
$var wire 1 * out_valid $end
$var wire 64 + test [63:0] $end
$var reg 1 $ clk $end
$var reg 64 , in_data [63:0] $end
$var reg 1600 - in_data_all_reg [1599:0] $end
$var reg 5 . in_round [4:0] $end
$var reg 5 / in_round_reg [4:0] $end
$var reg 1600 0 out_data_all_reg [1599:0] $end
$var integer 32 1 a [31:0] $end
$var integer 32 2 golden_read [31:0] $end
$var integer 32 3 patcount [31:0] $end
$scope task check_answer $end
$upscope $end
$scope task input_task $end
$upscope $end
$scope task load_golden $end
$upscope $end
$upscope $end
$upscope $end
$enddefinitions $end
#0
$dumpvars
bx 3
b10000000000000000000000000000011 2
bx 1
bx 0
bx /
bx .
bx -
bx ,
bx +
z*
bx )
bx (
bx '
bx &
bx %
0$
bx #
bx "
bx !
$end
#500
1$
#1000
b101100001011000010110000101100001011000010110000101100001011 +
b1000000010000000100000001000000010000000100000001000000011001010000010100000101000001010000010100000101000001010000010100010000111100001111000011110000111100001111000011110000111100001110000111100001111000011110000111100001111000011110000111100001111111100001111000011110000111100001111000011110000111100001111000001011100010111000101110001011100010111000101110001011100010111000111100001111000011110000111100001111000011110000111100001111000101100001011000010110000101100001011000010110000101100001011000001000000010000000100000001000000010000000100000001000000010000000100000101000001010000010100000101000001010000010100000101000001000111100001111000011110000111100001111000011110000111100001111000000000000000000000000000000000000000000000000000000000000000000000000100000001000000010000000100000001000000010000000100000001100011011000110110001101100011011000110110001101100011011000110100001010000010100000101000001010000010100000101000001010000010100111100001111000011110000111100001111000011110000111100001111000010100000101000001010000010100000101000001010000010100000101000011000011110000111100001111000011110000111100001111000011110000110100000101000001010000010100000101000001010000010100000101000001111100001111000011110000111100001111000011110000111100001111000001101100011011000110110001101100011011000110110001101100011011000101000001010000010100000101000001010000010100000101000001010000011101010111010101110101011101010111010101110101011101010111010111000011110000111100001111000011110000111100001111000011110000110000101100001011000010110000101100001011000010110000101100001011 0
b1000000010000000100000001000000010000000100000001000000010001010000010100000101000001010000010100000101000001010000010100010000111100001111000011110000111100001111000011110000111100001110000111100001111000011110000111100001111000011110000111100001111111100001111000011110000111100001111000011110000111100001111000001011100010111000101110001011100010111000101110001011100010111000111100001111000011110000111100001111000011110000111100001111000101100001011000010110000101100001011000010110000101100001011000001000000010000000100000001000000010000000100000001000000010000000100000101000001010000010100000101000001010000010100000101000001000111100001111000011110000111100001111000011110000111100001111000000000000000000000000000000000000000000000000000000000000000000000000100000001000000010000000100000001000000010000000100000001100011011000110110001101100011011000110110001101100011011000110100001010000010100000101000001010000010100000101000001010000010100111100001111000011110000111100001111000011110000111100001111000010100000101000001010000010100000101000001010000010100000101000011000011110000111100001111000011110000111100001111000011110000110100000101000001010000010100000101000001010000010100000101000001111100001111000011110000111100001111000011110000111100001111000001101100011011000110110001101100011011000110110001101100011011000101000001010000010100000101000001010000010100000101000001010000011101010111010101110101011101010111010101110101011101010111010111000011110000111100001111000011110000111100001111000011110000110000101100001011000010110000101100001011000010110000101100001011 -
b1 1
b0 /
b0 3
0$
#1500
1$
#2000
b1000000010000000100000001000000010000000100000001000000011 !
b1000000010000000100000001000000010000000100000001000000011 %
b1000000010000000100000001000000010000000100000001000000011 )
b1 (
b0 "
b0 &
b0 .
b1000000010000000100000001000000010000000100000001000000010 #
b1000000010000000100000001000000010000000100000001000000010 '
b1000000010000000100000001000000010000000100000001000000010 ,
0$
#2500
1$
#3000
b1010100010101000101010001010100010101000101010001010100010101100 +
b1010100010101000101010001010100010101000101010000010100000101011001111110011111100111111001111110011111100011111001111110011111101001101010011010100110101001101010011010100110101001101010010011101001111010011110100111101001111000011110100111101011111010011110011111100111111001111110011111100111111001111110011111100111111101011111010111111101111101011111010111110101111101011111010111110111011101110111011101110111011101110110011101110111011101110010001010100010101000101010001010100010101000101010001110100010100111000001110000011100000111000001110000011100000111100001110001110111111101111111011101110111111101111111011111110111111101111001001010010010100100101001001010010010100100101101001010010010101101000011010000100100001101000011010000110100001101000011010001111000011110000111100001111000011110000111100001111000011110000011001100110011001100110011001100110011001100110011000100110011001000101010001010100010001000101010001010100010101000101010000011101101111011011110110111101101111011011110110110101101111011011011111100111111001011110011111100111111001111110011111100111111010101001101010011010100110101001101010011010100110101011101011011100001011000010110000101100001011010010110000101100001011000010000011000000110000001100000011000000110000001100000011000000100001101100011011000111110001101100011011000110110011101100011011011010010110100101101001011010010110100101101001011010010110100101011010010110100101101001011010010110100101101001011010010110100101000011010000110100001101000011010000110100001101000011010000111010100010101000101010001010100010101000101010001010100010101100 0
b1010100010101000101010001010100010101000101010001010100010101001001111110011111100111111001111110011111100011111001111110011111101001101010011010100110101001101010011010100110101001101010010011101001111010011110100111101001111000011110100111101011111010011110011111100111111001111110011111100111111001111110011111100111111101011111010111111101111101011111010111110101111101011111010111110111011101110111011101110111011101110110011101110111011101110010001010100010101000101010001010100010101000101010001110100010100111000001110000011100000111000001110000011100000111100001110001110111111101111111011101110111111101111111011111110111111101111001001010010010100100101001001010010010100100101101001010010010101101000011010000100100001101000011010000110100001101000011010001111000011110000111100001111000011110000111100001111000011110000011001100110011001100110011001100110011001100110011000100110011001000101010001010100010001000101010001010100010101000101010000011101101111011011110110111101101111011011110110110101101111011011011111100111111001011110011111100111111001111110011111100111111010101001101010011010100110101001101010011010100110101011101011011100001011000010110000101100001011010010110000101100001011000010000011000000110000001100000011000000110000001100000011000000100001101100011011000111110001101100011011000110110011101100011011011010010110100101101001011010010110100101101001011010010110100101011010010110100101101001011010010110100101101001011010010110100101000011010000110100001101000011010000110100001101000011010000111010100010101000101010001010100010101000101010001010100010101100 -
b1 /
b1 3
0$
#3500
1$
#4000
b1000000010000010 (
b1010100010101000101010001010100010101000101010000010100000101011 !
b1010100010101000101010001010100010101000101010000010100000101011 %
b1010100010101000101010001010100010101000101010000010100000101011 )
b1 "
b1 &
b1 .
b1010100010101000101010001010100010101000101010001010100010101001 #
b1010100010101000101010001010100010101000101010001010100010101001 '
b1010100010101000101010001010100010101000101010001010100010101001 ,
0$
#4500
1$
#5000
b110000001100011011111100111001000101010111011000111000011011100 +
b101101011001010111010001100101011001100000000100100011011000110011111000111110101111100001101001001110000111100001111000110110011011111110111111101111011010111101111110001110011001001110000110101000011011001100110110101101100101001010110010101101011010011110011100000100101011101100111011100010111000101101011010100111100101001110000011110100100111001100111010111000100011001000110001010111010001100101010101000011000101110011111101111110010010000100100101010111011010010101001101001111001011010000111101001001010110011101101010111010111100101001101001000110010101101101101011111000000010010010110100100011111010111001100110101011110111101100111111010011110110011100101110001011010111101001101101011011001101011110010101011100111001011110001011000101110101001110000110010000111000001111000111100111111000101011110111110111111100011111101111111011011111110101111110111100011000100110000110111101000100011110101101000110000000011000000111101011100010011001010110111010101011111010100110110110110011100000111011101100101011011010111000111110010010101011011010110000100101001010011110111100110010100001111000101110000101110001011011000001000000010000011000000001000100001001110110110101011011000001000110010001000100011011000111111001111100100111000101010101000001010111000100100111011110000111010001111010011111000100010100100101001101001111010001110100001101010011000100110100011101100101011000100100000101010011001101010111010101111101011001001111001111000101110001011001010101101001000000110000010100001100100001010001010000000101001000110000001100011011111100111001000101010111011000111000011011100 0
b1101101011001010111010001100101011001100000000101100011001001100011111000111110101111100001101001001110000111100001111000110110011011111110111111101111011010111101111110001110011001001110000110101000011011001100110110101101100101001010110010101101011010011110011100000100101011101100111011100010111000101101011010100111100101001110000011110100100111001100111010111000100011001000110001010111010001100101010101000011000101110011111101111110010010000100100101010111011010010101001101001111001011010000111101001001010110011101101010111010111100101001101001000110010101101101101011111000000010010010110100100011111010111001100110101011110111101100111111010011110110011100101110001011010111101001101101011011001101011110010101011100111001011110001011000101110101001110000110010000111000001111000111100111111000101011110111110111111100011111101111111011011111110101111110111100011000100110000110111101000100011110101101000110000000011000000111101011100010011001010110111010101011111010100110110110110011100000111011101100101011011010111000111110010010101011011010110000100101001010011110111100110010100001111000101110000101110001011011000001000000010000011000000001000100001001110110110101011011000001000110010001000100011011000111111001111100100111000101010101000001010111000100100111011110000111010001111010011111000100010100100101001101001111010001110100001101010011000100110100011101100101011000100100000101010011001101010111010101111101011001001111001111000101110001011001010101101001000000110000010100001100100001010001010000000101001000110000001100011011111100111001000101010111011000111000011011100 -
b10 /
b10 3
0$
#5500
1$
#6000
b1000000000000000000000000000000000000000000000001000000010001010 (
b101101011001010111010001100101011001100000000100100011011000110 !
b101101011001010111010001100101011001100000000100100011011000110 %
b101101011001010111010001100101011001100000000100100011011000110 )
b10 "
b10 &
b10 .
b1101101011001010111010001100101011001100000000101100011001001100 #
b1101101011001010111010001100101011001100000000101100011001001100 '
b1101101011001010111010001100101011001100000000101100011001001100 ,
0$
#6500
1$
#7000
b101000101001110000101011111100010110000110001011100001100001100 +
b1110010100001101101100000000001010111101101101100010110111101010110001111000011000011000101110101101000111100000110110100110010110011101111100000100100001010001011010111110000101110011010000100000110101011101010001001011101101001011010101110010000001011100110101000011110001101001000000100110011001100011011001111100100101011110110110101011010100101000110100010000111101011011011111110001010100010101010011000111100111000001000101010011010111100010000001010001011100001110010001111101011111011001000101010000111101110011100000011101010010000110001010001010001001100010110000001110010111011100111001010010010010111000110001101110111001111110011100101011001100010110001100010001111111100000100110101111011100001001010011000010011101100111001000001100010101110101001110001011111110001010110110101110001110101101011001001001111100010001101001011010000001011101001011010110011001101111110101110101100010001101001111101000110011111010100010010011100110100010000011111111011001001010000010111011101000001110101011101000111101110101111100110101011111110010011000101101100111001010000101011001100110111111010101000100100111000101000000110001110110110101111111000110010011011101101101010000101000111001011011111000110101010000001101100111001110011110100111100011100010011001101000110010110001010010000100001010111101100011001010110101110000001110111000101111100110000001100100110111111110111001000111110101001001010101000111000001011101101100000001011000110110001111010000110001110110101010100001001001000100110100001000111110001010111110000100000101000101001110000101011111100010110000110001011100001100001100 0
b110010100001101101100000000001000111101101101101010110111101010110001111000011000011000101110101101000111100000110110100110010110011101111100000100100001010001011010111110000101110011010000100000110101011101010001001011101101001011010101110010000001011100110101000011110001101001000000100110011001100011011001111100100101011110110110101011010100101000110100010000111101011011011111110001010100010101010011000111100111000001000101010011010111100010000001010001011100001110010001111101011111011001000101010000111101110011100000011101010010000110001010001010001001100010110000001110010111011100111001010010010010111000110001101110111001111110011100101011001100010110001100010001111111100000100110101111011100001001010011000010011101100111001000001100010101110101001110001011111110001010110110101110001110101101011001001001111100010001101001011010000001011101001011010110011001101111110101110101100010001101001111101000110011111010100010010011100110100010000011111111011001001010000010111011101000001110101011101000111101110101111100110101011111110010011000101101100111001010000101011001100110111111010101000100100111000101000000110001110110110101111111000110010011011101101101010000101000111001011011111000110101010000001101100111001110011110100111100011100010011001101000110010110001010010000100001010111101100011001010110101110000001110111000101111100110000001100100110111111110111001000111110101001001010101000111000001011101101100000001011000110110001111010000110001110110101010100001001001000100110100001000111110001010111110000100000101000101001110000101011111100010110000110001011100001100001100 -
b11 /
b11 3
0$
#7500
1$
#8000
b1000000000000000000000000000000010000000000000001000000000000000 (
b1110010100001101101100000000001010111101101101100010110111101010 !
b1110010100001101101100000000001010111101101101100010110111101010 %
b1110010100001101101100000000001010111101101101100010110111101010 )
b11 "
b11 &
b11 .
b110010100001101101100000000001000111101101101101010110111101010 #
b110010100001101101100000000001000111101101101101010110111101010 '
b110010100001101101100000000001000111101101101101010110111101010 ,
0$
#8500
1$
#9000
b100100001000000111100001101000111100100101001000001110011111111 +
b111100001001111110011001010110110011110000100100000001100001010001101100011111011110010111110110000101000000001101000011100010101010001111011100000101010011011001000011000011101000011000011000001111111000100101000000101010110100000110101110001011111110010100111110101111000011001111010011001101011110110010010011100010010011111111100100000101011100100001010011111111011000100011110111101010100100010111010011111010011110101000111011101011100111001010001111010010110110101001101100101011100001001101100110100101000110100010001010110100111000001101011000001011011010100011010111101101001011010100101011101000011000001110101101000110100111011111011100100001101101101101001000100000001001110001010101000110100000101001101100000100101000000010000000011111111111101100101011001100010100010101110101111011010110111000101100110110011010100111001111101110101001100000110011001010101111101000110101110100110001011111000100111000010011101111000110011001000000110000000101100000000100001000101000110010100111000101000001011010111100100110100110111000100001001110110011010110110100001110111100000000101011111100100000001110111100011011010110011100011000110100111100100001001011001111010010010101110110001111101001101001101100101011100011110011101101110110001000010110001101000010011111101000110000010101001000101111000010011010100000111100001001101011111010101000111001111100001101010111111111110001011000101111011000111110000101110110010100111001110111011001010111000100101011010110011101001010000110100100110101111010110110101110001011000011011100100100001000000111100001101000111100100101001000001110011111111 0
b111100001001111110011001010110110011110000100101000001110000001001101100011111011110010111110110000101000000001101000011100010101010001111011100000101010011011001000011000011101000011000011000001111111000100101000000101010110100000110101110001011111110010100111110101111000011001111010011001101011110110010010011100010010011111111100100000101011100100001010011111111011000100011110111101010100100010111010011111010011110101000111011101011100111001010001111010010110110101001101100101011100001001101100110100101000110100010001010110100111000001101011000001011011010100011010111101101001011010100101011101000011000001110101101000110100111011111011100100001101101101101001000100000001001110001010101000110100000101001101100000100101000000010000000011111111111101100101011001100010100010101110101111011010110111000101100110110011010100111001111101110101001100000110011001010101111101000110101110100110001011111000100111000010011101111000110011001000000110000000101100000000100001000101000110010100111000101000001011010111100100110100110111000100001001110110011010110110100001110111100000000101011111100100000001110111100011011010110011100011000110100111100100001001011001111010010010101110110001111101001101001101100101011100011110011101101110110001000010110001101000010011111101000110000010101001000101111000010011010100000111100001001101011111010101000111001111100001101010111111111110001011000101111011000111110000101110110010100111001110111011001010111000100101011010110011101001010000110100100110101111010110110101110001011000011011100100100001000000111100001101000111100100101001000001110011111111 -
b100 /
b100 3
0$
#9500
1$
#10000
b1000000010001011 (
b111100001001111110011001010110110011110000100100000001100001010 !
b111100001001111110011001010110110011110000100100000001100001010 %
b111100001001111110011001010110110011110000100100000001100001010 )
b100 "
b100 &
b100 .
b111100001001111110011001010110110011110000100101000001110000001 #
b111100001001111110011001010110110011110000100101000001110000001 '
b111100001001111110011001010110110011110000100101000001110000001 ,
0$
#10500
1$
#11000
b1110101000111001101111100011000000110110110111011010001001101101 +
b10101110001110110011100001101111110001101101100011001100001101000010111100111011011001001101101011101111101110100101111110000010000111011110110100100010100111110100011001111010111110011010011000001010010001000100000101000101111111000101110100111100010011110101111101110000110110011111000101100011000011100010000001001111011010001011100110110111001001011010110001100000011100100011111111111111001010001111001011000100001110001100010010111110001111000110100110111110001001111111101100010111001101110111001100111001100100000010110100110100110000010001101110001000111110111101100001000011010100110000001010000101111100011101011101001111100110101001011001000010110100001010010011110011101101010011001111111010101111101110000110100001000011001011100111101111011010010100010000010011110011011100010001000100001001100010110100011011110011010011101111110110101101011010101001010010100011110001111101010111111001010111011011001001100001110111000001010101000100011001111100110111011000100001101001111101001000111001101010011000100000010011011000101000010011110101101010011110010111101100000001111010110100110101001101010000000101100010100000001001010010111010000111010011000111111010100001010010001110000000110111101100110111001110001000101110001000110111111110001001100111100010111000110111001011000000001000011101011110100111101011111001001110110011100010011011001110100111001011100001011100010110110101101110011001000001011111111111010011100001011110000110001010111001001011100010101101000001110000100100100101101000010100101101101001101010011110101000111001101111100011000000110110110111011010001001101101 0
b10101110001110110011100001101101110001101101100011001100001100000010111100111011011001001101101011101111101110100101111110000010000111011110110100100010100111110100011001111010111110011010011000001010010001000100000101000101111111000101110100111100010011110101111101110000110110011111000101100011000011100010000001001111011010001011100110110111001001011010110001100000011100100011111111111111001010001111001011000100001110001100010010111110001111000110100110111110001001111111101100010111001101110111001100111001100100000010110100110100110000010001101110001000111110111101100001000011010100110000001010000101111100011101011101001111100110101001011001000010110100001010010011110011101101010011001111111010101111101110000110100001000011001011100111101111011010010100010000010011110011011100010001000100001001100010110100011011110011010011101111110110101101011010101001010010100011110001111101010111111001010111011011001001100001110111000001010101000100011001111100110111011000100001101001111101001000111001101010011000100000010011011000101000010011110101101010011110010111101100000001111010110100110101001101010000000101100010100000001001010010111010000111010011000111111010100001010010001110000000110111101100110111001110001000101110001000110111111110001001100111100010111000110111001011000000001000011101011110100111101011111001001110110011100010011011001110100111001011100001011100010110110101101110011001000001011111111111010011100001011110000110001010111001001011100010101101000001110000100100100101101000010100101101101001101010011110101000111001101111100011000000110110110111011010001001101101 -
b101 /
b101 3
0$
#11500
1$
#12000
b10000000000000000000000000000001 (
b10101110001110110011100001101111110001101101100011001100001101 !
b10101110001110110011100001101111110001101101100011001100001101 %
b10101110001110110011100001101111110001101101100011001100001101 )
b101 "
b101 &
b101 .
b10101110001110110011100001101101110001101101100011001100001100 #
b10101110001110110011100001101101110001101101100011001100001100 '
b10101110001110110011100001101101110001101101100011001100001100 ,
0$
#12500
1$
#13000
b1001000101010110001000011011101000011100000001000000000010111111 +
b11101000001011100100110100001111111000101010011000100000010011000101111100111111010001011110110001001010101111110111011101000100011001001011011000000111010010110000000110011101111100111110111011011100111100000000100000010101011010101100110010101010110100000010111111010010100001110011000110010100101101010010010011111000010101010011010110010111111110101100101101110101010001000001111100111100010011110001101001010000001101110010010100111010000100010111101000011111011111101110011101000010101100100110011100010111111010101100111000111101110110111101101111000101100110111001111101001101010101011101101001110110100100110001001111011001111101101100111110111110111101010000011111000100011000010011011000110111010110100001101110111111111100100011001000110100001011101111011011110101100110101101001100100000100100101101100101001011111111100110100001010010000111111110100010011010001010010110101100101100011101011000111001100001000101011111001100010100000000110010001101000100110111100000010100101110000001011110110111010001001100110011111001110110110100100000011101101000101100001100111001010000010001100100010110110101010000010110010000001011001010001100010101110010011001100011100111011011001110110010001111101000001110000101100110000100000001011100100100110010100010010110001111111010011110111010100111010101001111011010010101010001111100110000101110100001110011101100101000101101000111110010010000011111001000110010101000010101110101010110111101011110011011101110001110101100111100110111010110101110110110011001101101100011111010111011111001000101010110001000011011101000011100000001000000000010111111 0
b1011101000001011100100110100001101111000101010010000100010010010000101111100111111010001011110110001001010101111110111011101000100011001001011011000000111010010110000000110011101111100111110111011011100111100000000100000010101011010101100110010101010110100000010111111010010100001110011000110010100101101010010010011111000010101010011010110010111111110101100101101110101010001000001111100111100010011110001101001010000001101110010010100111010000100010111101000011111011111101110011101000010101100100110011100010111111010101100111000111101110110111101101111000101100110111001111101001101010101011101101001110110100100110001001111011001111101101100111110111110111101010000011111000100011000010011011000110111010110100001101110111111111100100011001000110100001011101111011011110101100110101101001100100000100100101101100101001011111111100110100001010010000111111110100010011010001010010110101100101100011101011000111001100001000101011111001100010100000000110010001101000100110111100000010100101110000001011110110111010001001100110011111001110110110100100000011101101000101100001100111001010000010001100100010110110101010000010110010000001011001010001100010101110010011001100011100111011011001110110010001111101000001110000101100110000100000001011100100100110010100010010110001111111010011110111010100111010101001111011010010101010001111100110000101110100001110011101100101000101101000111110010010000011111001000110010101000010101110101010110111101011110011011101110001110101100111100110111010110101110110110011001101101100011111010111011111001000101010110001000011011101000011100000001000000000010111111 -
b110 /
b110 3
0$
#13500
1$
#14000
b1000000000000000000000000000000010000000000000001000000010000001 (
b11101000001011100100110100001111111000101010011000100000010011 !
b11101000001011100100110100001111111000101010011000100000010011 %
b11101000001011100100110100001111111000101010011000100000010011 )
b110 "
b110 &
b110 .
b1011101000001011100100110100001101111000101010010000100010010010 #
b1011101000001011100100110100001101111000101010010000100010010010 '
b1011101000001011100100110100001101111000101010010000100010010010 ,
0$
#14500
1$
